{
  "openapi": "3.0.0",
  "info": {
    "title": "Taskify",
    "description": "Taskify API",
    "components": {
      "securitySchemes": {
        "bearerAuth": {
          "type": "http",
          "scheme": "bearer",
          "bearerFormat": "jwt"
        }
      }
    },
    "version": "1.0.0"
  },
  "servers": [
    {
      "url": "http://localhost:5200"
    }
  ],
  "paths": {
    "/auth/signup": {
      "post": {
        "tags": [
          "Auth"
        ],
        "description": "",
        "responses": {
          "200": {
            "description": "OK"
          },
          "400": {
            "description": "Bad Request"
          },
          "500": {
            "description": "Internal Server Error"
          }
        },
        "requestBody": {
          "description": "Optional description in *Markdown*",
          "required": true,
          "content": {
            "application/json": {
              "schema": {
                "$ref": "#/components/schemas/user"
              }
            }
          }
        }
      }
    },
    "/auth/signin": {
      "post": {
        "tags": [
          "Auth"
        ],
        "description": "",
        "responses": {
          "200": {
            "description": "OK"
          },
          "401": {
            "description": "Unauthorized"
          },
          "500": {
            "description": "Internal Server Error"
          }
        },
        "requestBody": {
          "content": {
            "application/json": {
              "schema": {
                "type": "object",
                "properties": {
                  "email": {
                    "example": "any"
                  },
                  "password": {
                    "example": "any"
                  }
                }
              }
            }
          }
        }
      }
    },
    "/auth/logout": {
      "get": {
        "tags": [
          "Auth"
        ],
        "description": "",
        "parameters": [
          {
            "name": "Authorization",
            "in": "header",
            "schema": {
              "type": "string"
            }
          }
        ],
        "responses": {
          "200": {
            "description": "OK"
          },
          "400": {
            "description": "Bad Request"
          },
          "500": {
            "description": "Internal Server Error"
          }
        },
        "security": [
          {
            "Bearer": []
          }
        ]
      }
    },
    "/auth/logoutAll": {
      "get": {
        "tags": [
          "Auth"
        ],
        "description": "",
        "responses": {
          "200": {
            "description": "OK"
          },
          "400": {
            "description": "Bad Request"
          },
          "500": {
            "description": "Internal Server Error"
          }
        },
        "security": [
          {
            "Bearer": []
          }
        ]
      }
    },
    "/taskify/tasks": {
      "get": {
        "tags": [
          "Task"
        ],
        "description": "",
        "parameters": [
          {
            "name": "dueDate",
            "in": "query",
            "schema": {
              "type": "string"
            }
          },
          {
            "name": "priority",
            "in": "query",
            "schema": {
              "type": "enum",
              "enum": [
                "High",
                "Low",
                "Medium"
              ]
            }
          },
          {
            "name": "status",
            "in": "query",
            "schema": {
              "type": "enum",
              "enum": [
                "Pending",
                "Completed"
              ]
            }
          }
        ],
        "responses": {
          "200": {
            "description": "OK"
          },
          "400": {
            "description": "Bad Request"
          },
          "500": {
            "description": "Internal Server Error"
          }
        },
        "security": [
          {
            "Bearer": []
          }
        ]
      },
      "post": {
        "tags": [
          "Task"
        ],
        "description": "",
        "responses": {
          "200": {
            "description": "OK"
          },
          "400": {
            "description": "Bad Request"
          },
          "500": {
            "description": "Internal Server Error"
          }
        },
        "security": [
          {
            "Bearer": []
          }
        ],
        "requestBody": {
          "description": "Optional description in *Markdown*",
          "required": true,
          "content": {
            "application/json": {
              "schema": {
                "$ref": "#/components/schemas/task"
              }
            }
          }
        }
      }
    },
    "/taskify/tasks/{id}": {
      "get": {
        "tags": [
          "Task"
        ],
        "description": "",
        "parameters": [
          {
            "name": "id",
            "in": "path",
            "required": true,
            "schema": {
              "type": "string"
            }
          }
        ],
        "responses": {
          "200": {
            "description": "OK"
          },
          "400": {
            "description": "Bad Request"
          },
          "404": {
            "description": "Not Found"
          }
        },
        "security": [
          {
            "Bearer": []
          }
        ]
      },
      "put": {
        "tags": [
          "Task"
        ],
        "description": "",
        "parameters": [
          {
            "name": "id",
            "in": "path",
            "required": true,
            "schema": {
              "type": "string"
            }
          }
        ],
        "responses": {
          "200": {
            "description": "OK"
          },
          "400": {
            "description": "Bad Request"
          },
          "500": {
            "description": "Internal Server Error"
          }
        },
        "security": [
          {
            "Bearer": []
          }
        ],
        "requestBody": {
          "description": "Optional description in *Markdown*",
          "required": true,
          "content": {
            "application/json": {
              "schema": {
                "$ref": "#/components/schemas/task"
              }
            }
          }
        }
      },
      "delete": {
        "tags": [
          "Task"
        ],
        "description": "",
        "parameters": [
          {
            "name": "id",
            "in": "path",
            "required": true,
            "schema": {
              "type": "string"
            }
          }
        ],
        "responses": {
          "200": {
            "description": "OK"
          },
          "400": {
            "description": "Bad Request"
          },
          "500": {
            "description": "Internal Server Error"
          }
        },
        "security": [
          {
            "Bearer": []
          }
        ]
      }
    }
  },
  "components": {
    "schemas": {
      "task": {
        "type": "object",
        "properties": {
          "title": {
            "type": "string",
            "example": "string"
          },
          "description": {
            "type": "string",
            "example": "string"
          },
          "dueDate": {
            "type": "string",
            "example": "string"
          },
          "priority": {
            "type": "string",
            "example": "string"
          },
          "status": {
            "type": "string",
            "example": "string"
          }
        }
      },
      "user": {
        "type": "object",
        "properties": {
          "name": {
            "type": "string",
            "example": "string"
          },
          "email": {
            "type": "string",
            "example": "string"
          },
          "password": {
            "type": "string",
            "example": "string"
          }
        }
      }
    },
    "securitySchemes": {
      "Bearer": {
        "type": "apiKey",
        "name": "Authorization",
        "in": "header",
        "description": " Enter the token with the`Bearer: ` prefix, e.g. \"Bearer abcde12345\""
      }
    }
  }
}
